CHANGES.txt
LICENSE.txt
MANIFEST.in
README.txt
setup.py
src/j01/__init__.py
src/j01.selectordered.egg-info/PKG-INFO
src/j01.selectordered.egg-info/SOURCES.txt
src/j01.selectordered.egg-info/dependency_links.txt
src/j01.selectordered.egg-info/namespace_packages.txt
src/j01.selectordered.egg-info/not-zip-safe
src/j01.selectordered.egg-info/requires.txt
src/j01.selectordered.egg-info/top_level.txt
src/j01/selectordered/__init__.py
src/j01/selectordered/configure.zcml
src/j01/selectordered/interfaces.py
src/j01/selectordered/layer.py
src/j01/selectordered/widget.py
src/j01/selectordered/widget_input.pt
src/j01/selectordered/widget_input_from.pt
src/j01/selectordered/widget_input_to.pt
src/j01/selectordered/tests/__init__.py
src/j01/selectordered/tests/checker.txt
src/j01/selectordered/tests/tests.py