Metadata-Version: 1.1
Name: j01.selectordered
Version: 0.5.2
Summary: Ordered select widget based on JQuery and z3c.form for Zope 3
Home-page: http://pypi.python.org/pypi/j01.selectordered
Author: Roger Ineichen, Projekt01 GmbH
Author-email: dev@projekt01.ch
License: ZPL 2.1
Keywords: J01 z3c ordered select widget form JQuery Zope3
Platform: UNKNOWN
Classifier: Development Status :: 5 - Production/Stable
Classifier: Environment :: Web Environment
Classifier: Intended Audience :: Developers
Classifier: License :: OSI Approved :: Zope Public License
Classifier: Programming Language :: Python
Classifier: Natural Language :: English
Classifier: Operating System :: OS Independent
Classifier: Topic :: Internet :: WWW/HTTP
Classifier: Framework :: Zope3
